paraparser/__init__.py
paraparser/parameters.py
paraparser-1.0.0.dist-info/DESCRIPTION.rst
paraparser-1.0.0.dist-info/METADATA
paraparser-1.0.0.dist-info/RECORD
paraparser-1.0.0.dist-info/WHEEL
paraparser-1.0.0.dist-info/metadata.json
paraparser-1.0.0.dist-info/top_level.txt
