Metadata-Version: 2.0
Name: paraparser
Version: 1.0.0
Summary: parameters process
Home-page: https://github.com/sky-y-zhang/paraparser.git
Author: Sky Zhang
Author-email: zyx474029625@126.com
License: MIT Licence
Keywords: pip,parameters,parser
Platform: any
Requires-Dist: six
